Workbook
Name aporte: APP!$H$20
Name patrimonio: APP!$H$23
Name qtd_anos: APP!$H$21
Name rendimento_carteira: APP!$H$15
Name salario: APP!$H$14
Name taxa_mensal: APP!$H$22

Sheet APP
B12: CONFIGURAÇÕES
B14: Salário | H14: 5000
B15: Rendimento Carteira | H15: 0.006
B16: Sugestão de Investimento (30%) | H16: =$H$14*0.3 -> 1500
B18: INVESTIMENTO MENSAL
B20: Quanto investir por mês ? | H20: 500
B21: Por Quantos Anos ? | H21: 5
B22: Taxa de Rendimento mensal ? | H22: 0.01079
B23: Patrimônio acumulado ? | H23: =FV(taxa_mensal,qtd_anos*12,aporte*-1) -> 41888.457
B24: Dividendos Mensais ? | H24: =patrimonio*rendimento_carteira -> 251.33074
B26: CENÁRIOS | I26: DIVIDENDOS
A28: 2 | B28: Quanto em 2 Anos ? | G28: =FV($H$22,$A28*12,$H$20*-1) -> 13613.814 | I28: =G28*rendimento_carteira -> 81.682882
A29: 5 | B29: Quanto em 5 Anos ? | G29: =FV($H$22,$A29*12,$H$20*-1) -> 41888.457 | I29: =G29*rendimento_carteira -> 251.33074
A30: 10 | B30: Quanto em 10 Anos ? | G30: =FV($H$22,$A30*12,$H$20*-1) -> 121642.11 | I30: =G30*rendimento_carteira -> 729.85264
A31: 20 | B31: Quanto em 20 Anos ? | G31: =FV($H$22,$A31*12,$H$20*-1) -> 562599.2 | I31: =G31*rendimento_carteira -> 3375.5952
A32: 30 | B32: Quanto em 30 Anos ? | G32: =FV($H$22,$A32*12,$H$20*-1) -> 2161084.8 | I32: =G32*rendimento_carteira -> 12966.509
B35: PERFIL | H35: Moderado
B36: VALOR A SER INVESTIDO POR MÊS | H36: =aporte -> 500
B38: TIPO DE FII | G38: Percentual Sugerido | I38: Valores
B39: PAPEL | G39: =VLOOKUP($H$35&"-"&B39,PERFIL!$A:$D,4,FALSE) -> 0.32 | I39: =G39*aporte -> 160
B40: TIJOLO | G40: =VLOOKUP($H$35&"-"&B40,PERFIL!$A:$D,4,FALSE) -> 0.35 | I40: =G40*aporte -> 175
B41: HÍBRIDOS | G41: =VLOOKUP($H$35&"-"&B41,PERFIL!$A:$D,4,FALSE) -> 0.08 | I41: =G41*aporte -> 40
B42: FOFs | G42: =VLOOKUP($H$35&"-"&B42,PERFIL!$A:$D,4,FALSE) -> 0.05 | I42: =G42*aporte -> 25
B43: DESENVOLVIMENTO | G43: =VLOOKUP($H$35&"-"&B43,PERFIL!$A:$D,4,FALSE) -> 0.1 | I43: =G43*aporte -> 50
B44: HOTELARIAS | G44: =VLOOKUP($H$35&"-"&B44,PERFIL!$A:$D,4,FALSE) -> 0.1 | I44: =G44*aporte -> 50
I45: =SUM(I39:I44) -> 500

Sheet PERFIL
A2: CHAVE | B2: PERFIL | C2: TIPO DE FII | D2: %
A3: =B3&"-"&C3 -> Conservador-PAPEL | B3: Conservador | C3: PAPEL | D3: 0.3 | H3: %
A4: =B4&"-"&C4 -> Conservador-TIJOLO | B4: Conservador | C4: TIJOLO | D4: 0.5 | G4: Moderado-TIJOLO | H4: =VLOOKUP(G4,$A:$D,4,FALSE) -> 0.35
A5: =B5&"-"&C5 -> Conservador-HÍBRIDOS | B5: Conservador | C5: HÍBRIDOS | D5: 0.1
A6: =B6&"-"&C6 -> Conservador-FOFs | B6: Conservador | C6: FOFs | D6: 0.1
A7: =B7&"-"&C7 -> Conservador-DESENVOLVIMENTO | B7: Conservador | C7: DESENVOLVIMENTO | D7: 0
A8: =B8&"-"&C8 -> Conservador-HOTELARIAS | B8: Conservador | C8: HOTELARIAS | D8: 0
A9: =B9&"-"&C9 -> Moderado-PAPEL | B9: Moderado | C9: PAPEL | D9: 0.32
A10: =B10&"-"&C10 -> Moderado-TIJOLO | B10: Moderado | C10: TIJOLO | D10: 0.35
A11: =B11&"-"&C11 -> Moderado-HÍBRIDOS | B11: Moderado | C11: HÍBRIDOS | D11: 0.08
A12: =B12&"-"&C12 -> Moderado-FOFs | B12: Moderado | C12: FOFs | D12: 0.05
A13: =B13&"-"&C13 -> Moderado-DESENVOLVIMENTO | B13: Moderado | C13: DESENVOLVIMENTO | D13: 0.1
A14: =B14&"-"&C14 -> Moderado-HOTELARIAS | B14: Moderado | C14: HOTELARIAS | D14: 0.1
A15: =B15&"-"&C15 -> Agressivo-PAPEL | B15: Agressivo | C15: PAPEL | D15: 0.5
A16: =B16&"-"&C16 -> Agressivo-TIJOLO | B16: Agressivo | C16: TIJOLO | D16: 0.1
... A20: =B20&"-"&C20 -> Agressivo-HOTELARIAS | B20: Agressivo | C20: HOTELARIAS | D20: 0.1
